numformat/__init__.py
numformat/formatter.py
numformat/numformat.py
numformat/utils.py
numformat/operators/__init__.py
numformat/operators/decimal_operator.py
numformat/operators/integer_operator.py
numformat/operators/operator.py
numformat/operators/operator_factory.py
numformat-0.0.4.dist-info/LICENSE
numformat-0.0.4.dist-info/METADATA
numformat-0.0.4.dist-info/WHEEL
numformat-0.0.4.dist-info/top_level.txt
numformat-0.0.4.dist-info/RECORD
