Metadata-Version: 2.1
Name: numformat
Version: 0.0.4
Summary: A package that helps you format numbers for engineering, scientific, and UI applications.
Home-page: https://github.com/sgowris2/numformat
Author: Sudeep Gowrishankar
Author-email: sgowris2@gmail.com
License: UNKNOWN
Project-URL: Bug Tracker, https://github.com/sgowris2/numformat/issues
Platform: UNKNOWN
Classifier: Programming Language :: Python :: 3
Classifier: License :: OSI Approved :: MIT License
Classifier: Operating System :: OS Independent
Requires-Python: >=3.6
